aws_pc/__init__.py
aws_pc/config.py
aws_pc/iam.py
aws_pc/organization.py
aws_pc/policy.py
aws_pc/s3.py
aws_pc/sso.py
aws_pc/create_roles/create_roles.py
aws_pc/create_roles/delete_roles.py
aws_pc/update_contact_details/update_details.py
aws_pc-0.3.0.dist-info/LICENCE
aws_pc-0.3.0.dist-info/METADATA
aws_pc-0.3.0.dist-info/WHEEL
aws_pc-0.3.0.dist-info/top_level.txt
aws_pc-0.3.0.dist-info/RECORD
