Metadata-Version: 2.1
Name: aws_pc
Version: 0.3.0
Summary: Methods and objects for interfacing with AWS through boto3.
Author: Peter Crowther
Project-URL: Homepage, https://github.com/merrygoat/aws_pc
License-File: LICENCE
